{"time": ["None", 89.335, 136.541, 89.368, 135.985, 88.834, 133.654, 143.834, 89.17, 95.437, "None", 87.916, 111.675, "None", 93.286, 93.602, 93.358, 93.384, 94.023, 94.535, 94.694, 110.951, "None", 130.482, "None"], "lap": [1.0, 2.0, 3.0, 4.0, 5.0, 6.0, 7.0, 8.0, 9.0, 10.0, 11.0, 12.0, 13.0, 14.0, 15.0, 16.0, 17.0, 18.0, 19.0, 20.0, 21.0, 22.0, 23.0, 24.0, 25.0], "compound": ["MEDIUM", "MEDIUM", "MEDIUM", "MEDIUM", "MEDIUM", "MEDIUM", "MEDIUM", "MEDIUM", "MEDIUM", "MEDIUM", "SOFT", "SOFT", "SOFT", "SOFT", "SOFT", "SOFT", "SOFT", "SOFT", "SOFT", "SOFT", "SOFT", "SOFT", "INTERMEDIATE", "INTERMEDIATE", "INTERMEDIATE"], "stint": [1, 1, 1, 1, 1, 1, 1, 2, 2, 2, 3, 3, 3, 4, 4, 4, 4, 4, 4, 4, 4, 4, 5, 5, 5], "s1": ["None", 28.462, 46.628, 28.562, 44.829, 28.335, 42.83, 66.291, 28.527, 30.879, "None", 28.129, 42.494, "None", 29.624, 29.76, 29.723, 29.727, 29.859, 30.072, 30.07, 31.836, "None", 38.047, 68.447], "s2": [42.902, 36.461, 47.847, 36.343, 55.854, 36.22, 58.659, 42.53, 36.242, 38.964, 43.929, 35.67, 42.654, 38.324, 38.019, 38.064, 37.953, 37.965, 38.202, 38.468, 38.42, 47.087, 55.512, 51.764, 51.221], "s3": [40.327, 24.412, 42.066, 24.463, 35.302, 24.279, 32.165, 35.013, 24.401, 25.594, 29.131, 24.117, 26.527, 25.759, 25.643, 25.778, 25.682, 25.692, 25.962, 25.995, 26.204, 32.028, 35.442, 40.671, 32.484], "life": [1, 2, 3, 4, 5, 6, 7, 8, 9, 10, 1, 2, 3, 4, 5, 6, 7, 8, 9, 10, 11, 12, 1, 2, 3], "pos": ["None", "None", "None", "None", "None", "None", "None", "None", "None", "None", "None", "None", "None", "None", "None", "None", "None", "None", "None", "None", "None", "None", "None", "None", "None"], "status": ["1", "1", "1", "1", "1", "1", "1", "1", "1", "1", "1", "1", "1", "1", "1", "1", "1", "1", "1", "1", "1", "1", "1", "1", "1"], "pb": [false, true, false, false, false, true, false, false, false, false, false, true, false, false, false, false, false, false, false, false, false, false, false, false, false]}