{"time": [92.353, 87.135, 73.328, 115.799, 72.702, 99.155, 72.478, 106.431, 98.981, 71.753, 102.38, 71.623, "None", 90.702, 84.76, 71.66, 98.414, 71.607, "None", 92.438, 71.216, 96.792, "None", 91.99, 71.805, 111.754, 89.313, 70.948, "None"], "lap": [1.0, 2.0, 3.0, 4.0, 5.0, 6.0, 7.0, 8.0, 9.0, 10.0, 11.0, 12.0, 13.0, 14.0, 15.0, 16.0, 17.0, 18.0, 19.0, 20.0, 21.0, 22.0, 23.0, 24.0, 25.0, 26.0, 27.0, 28.0, 29.0], "compound": ["SOFT", "SOFT", "SOFT", "SOFT", "SOFT", "SOFT", "SOFT", "SOFT", "SOFT", "SOFT", "SOFT", "SOFT", "SOFT", "SOFT", "SOFT", "SOFT", "SOFT", "SOFT", "SOFT", "SOFT", "SOFT", "SOFT", "SOFT", "SOFT", "SOFT", "SOFT", "SOFT", "SOFT", "SOFT"], "stint": [1, 1, 1, 1, 1, 1, 1, 1, 2, 2, 2, 2, 2, 3, 3, 3, 3, 3, 3, 4, 4, 4, 4, 5, 5, 5, 6, 6, 6], "s1": [29.645, 20.288, 18.96, 35.425, 19.007, 26.453, 18.765, 21.765, 28.246, 18.748, 26.335, 18.635, 24.382, 28.374, 18.843, 18.823, 27.284, 18.709, 20.832, 28.14, 18.594, 24.394, 18.85, 28.335, 18.718, 22.749, 28.413, 18.487, 25.844], "s2": [40.992, 39.293, 34.638, 47.148, 34.544, 47.291, 34.482, 41.043, 41.871, 33.94, 46.569, 33.925, 42.874, 40.584, 44.279, 33.833, 46.844, 33.899, 37.827, 41.845, 33.684, 46.933, 34.936, 41.248, 34.052, 41.103, 39.761, 33.597, 42.664], "s3": [21.716, 27.554, 19.73, 33.226, 19.151, 25.411, 19.231, 43.623, 28.864, 19.065, 29.476, 19.063, "None", 21.744, 21.638, 19.004, 24.286, 18.999, "None", 22.453, 18.938, 25.465, "None", 22.407, 19.035, 47.902, 21.139, 18.864, "None"], "life": [1, 2, 3, 4, 5, 6, 7, 8, 1, 2, 3, 4, 5, 1, 2, 3, 4, 5, 6, 1, 2, 3, 4, 5, 6, 7, 1, 2, 3], "pos": ["None", "None", "None", "None", "None", "None", "None", "None", "None", "None", "None", "None", "None", "None", "None", "None", "None", "None", "None", "None", "None", "None", "None", "None", "None", "None", "None", "None", "None"], "status": ["1", "1", "1", "1", "1", "1", "1", "1", "12", "1", "1", "1", "12", "1", "1", "1", "1", "1", "1", "1", "1", "1", "12", "1", "1", "1", "1", "1", "1"], "pb": [false, true, true, false, true, false, true, false, false, true, false, true, false, false, true, true, false, true, false, false, true, false, false, false, true, false, false, true, false]}