{"time": ["None", 101.118, "None", "None", 99.297, 139.911, 98.13, "None", 136.021, 98.09, 118.088, "None", 98.698, 134.833, 121.087, 100.675, 101.119, 101.787, 131.084, 127.486], "lap": [1.0, 2.0, 3.0, 4.0, 5.0, 6.0, 7.0, 8.0, 9.0, 10.0, 11.0, 12.0, 13.0, 14.0, 15.0, 16.0, 17.0, 18.0, 19.0, 20.0], "compound": ["SOFT", "SOFT", "SOFT", "SOFT", "SOFT", "SOFT", "SOFT", "SOFT", "SOFT", "SOFT", "SOFT", "SOFT", "SOFT", "SOFT", "SOFT", "SOFT", "SOFT", "SOFT", "SOFT", "SOFT"], "stint": [1, 1, 1, 2, 2, 2, 2, 2, 2, 2, 2, 3, 3, 3, 3, 3, 3, 3, 3, 3], "s1": ["None", 26.561, 36.009, "None", 26.162, 35.207, 25.82, 34.043, 26.018, 25.768, 30.801, "None", 25.872, 34.988, 26.171, 26.502, 26.766, 26.755, 31.863, 44.623], "s2": [35.013, 30.371, "None", 31.921, 29.62, 47.835, 29.208, 51.533, 39.891, 29.132, 33.56, 35.02, 29.747, 45.111, 33.045, 29.972, 29.963, 30.307, 41.195, 30.061], "s3": [61.879, 44.186, "None", 48.111, 43.515, 56.869, 43.102, 80.273, 70.112, 43.19, 53.727, 48.35, 43.079, 54.734, 61.871, 44.201, 44.39, 44.725, 58.026, 52.802], "life": [1, 2, 3, 4, 5, 6, 7, 8, 9, 10, 11, 12, 13, 14, 15, 16, 17, 18, 19, 20], "pos": ["None", "None", "None", "None", "None", "None", "None", "None", "None", "None", "None", "None", "None", "None", "None", "None", "None", "None", "None", "None"], "status": ["1", "1", "15", "1", "1", "1", "1", "1", "1", "1", "1", "1", "1", "1", "1", "1", "1", "1", "1", "1"], "pb": [false, true, false, false, true, false, true, false, false, true, false, false, false, false, false, false, false, false, false, false]}