{"time": [107.225, 80.039, 104.998, 78.979, "None", 91.126, 79.14, 137.205, 77.822, 124.811, 78.294, "None", 118.191, 83.431, 83.21, 82.842, 83.133, 83.006, 83.329, 83.12, 83.749, 91.435, 84.4, 92.974, 120.891, 98.177, 82.022, "None", "None"], "lap": [1.0, 2.0, 3.0, 4.0, 5.0, 6.0, 7.0, 8.0, 9.0, 10.0, 11.0, 12.0, 13.0, 14.0, 15.0, 16.0, 17.0, 18.0, 19.0, 20.0, 21.0, 22.0, 23.0, 24.0, 25.0, 26.0, 27.0, 28.0, 29.0], "compound": ["MEDIUM", "MEDIUM", "MEDIUM", "MEDIUM", "MEDIUM", "SOFT", "SOFT", "SOFT", "SOFT", "SOFT", "SOFT", "SOFT", "MEDIUM", "MEDIUM", "MEDIUM", "MEDIUM", "MEDIUM", "MEDIUM", "MEDIUM", "MEDIUM", "MEDIUM", "MEDIUM", "MEDIUM", "MEDIUM", "MEDIUM", "SOFT", "SOFT", "SOFT", "SOFT"], "stint": [1, 1, 1, 1, 1, 2, 2, 2, 2, 2, 2, 2, 3, 3, 3, 3, 3, 3, 3, 3, 3, 3, 3, 3, 3, 4, 4, 4, 4], "s1": [37.4, 28.064, 35.001, 27.561, 40.759, 36.236, 26.777, 48.929, 26.831, 46.773, 27.125, 38.282, 60.561, 29.013, 28.865, 28.857, 28.887, 28.895, 28.974, 28.857, 29.085, 29.568, 29.319, 29.112, 36.183, 37.433, 28.27, 35.82, 31.763], "s2": [18.653, 18.103, 26.922, 17.907, 28.744, 18.842, 17.691, 34.84, 17.798, 32.582, 17.853, 19.817, 19.398, 18.825, 18.714, 18.688, 18.738, 18.587, 18.634, 18.658, 18.637, 18.481, 18.731, 18.743, 23.923, 19.094, 18.434, 24.838, 18.758], "s3": [51.172, 33.872, 43.075, 33.511, "None", 36.048, 34.672, 53.436, 33.193, 45.456, 33.316, "None", 38.232, 35.593, 35.631, 35.297, 35.508, 35.524, 35.721, 35.605, 36.027, 43.386, 36.35, 45.119, 60.785, 41.65, 35.318, 90.903, "None"], "life": [1, 2, 3, 4, 5, 1, 2, 3, 4, 5, 6, 7, 6, 7, 8, 9, 10, 11, 12, 13, 14, 15, 16, 17, 18, 8, 9, 10, 11], "pos": ["None", "None", "None", "None", "None", "None", "None", "None", "None", "None", "None", "None", "None", "None", "None", "None", "None", "None", "None", "None", "None", "None", "None", "None", "None", "None", "None", "None", "None"], "status": ["1", "1", "1", "1", "12", "1", "1", "1", "1", "1", "1", "1", "1", "1", "1", "1", "1", "1", "1", "1", "1", "1", "1", "1", "1", "1", "1", "1", "1"], "pb": [false, true, false, true, false, false, false, false, true, false, false, false, false, false, false, false, false, false, false, false, false, false, false, false, false, false, false, false, false]}