{"time": ["None", 112.601, 95.625, 139.069, 94.883, 119.404, 144.471, "None", 112.293, "None", "None", 102.284, 136.955], "lap": [1.0, 2.0, 3.0, 4.0, 5.0, 6.0, 7.0, 8.0, 9.0, 10.0, 11.0, 12.0, 13.0], "compound": ["SOFT", "SOFT", "SOFT", "SOFT", "SOFT", "SOFT", "SOFT", "SOFT", "SOFT", "SOFT", "SOFT", "SOFT", "SOFT"], "stint": [1, 1, 1, 1, 1, 1, 2, 3, 3, 3, 4, 4, 4], "s1": ["None", 33.197, 27.299, 40.928, 26.877, 36.162, 62.7, "None", 38.849, 26.499, "None", 26.588, 59.319], "s2": [36.653, 40.373, 31.944, 53.467, 31.624, 38.681, 37.281, 39.293, 34.737, "None", 35.385, 31.501, 34.028], "s3": [44.463, 39.031, 36.382, 44.674, 36.382, 44.561, 44.49, 40.641, 38.707, "None", 38.923, 44.195, 43.608], "life": [1, 2, 3, 4, 5, 6, 7, 1, 2, 3, 4, 5, 6], "pos": ["None", "None", "None", "None", "None", "None", "None", "None", "None", "None", "None", "None", "None"], "status": ["1", "1", "12", "1", "1", "12", "1", "1", "1", "125", "1", "1", "1"], "pb": [false, true, true, false, true, false, false, false, false, false, false, false, false]}