{"time": ["None", 78.069, "None", 139.195, "None", "None", 77.079, 127.479, 130.412, 76.96, 85.381, "None", "None", "None", 97.649, "None"], "lap": [1.0, 2.0, 3.0, 4.0, 5.0, 6.0, 7.0, 8.0, 9.0, 10.0, 11.0, 12.0, 13.0, 14.0, 15.0, 16.0], "compound": ["SOFT", "SOFT", "SOFT", "SOFT", "SOFT", "SOFT", "SOFT", "SOFT", "SOFT", "SOFT", "SOFT", "SOFT", "SOFT", "SOFT", "SOFT", "SOFT"], "stint": [1, 1, 1, 1, 1, 2, 2, 2, 2, 2, 2, 3, 3, 4, 4, 4], "s1": ["None", 24.457, 52.03, 48.627, 24.387, "None", 24.408, 41.731, 42.859, 24.316, 25.657, "None", "None", "None", 24.202, 66.954], "s2": [36.331, 27.209, 57.927, 53.955, "None", 35.625, 26.659, 48.685, 50.603, 26.699, 28.264, 35.692, "None", 30.8, 26.403, 55.324], "s3": [31.461, 26.403, 50.277, 36.613, "None", 28.934, 26.012, 37.063, 36.95, 25.945, 31.46, 38.293, "None", 28.837, 47.044, 34.269], "life": [1, 2, 3, 4, 5, 6, 7, 8, 9, 10, 11, 1, 2, 3, 4, 5], "pos": ["None", "None", "None", "None", "None", "None", "None", "None", "None", "None", "None", "None", "None", "None", "None", "None"], "status": ["1", "1", "1", "1", "125", "1", "1", "1", "1", "1", "1", "12", "251", "1", "1", "1"], "pb": [false, true, false, false, false, false, true, false, false, true, false, false, false, false, false, false]}