{"time": ["None", 94.488, "None", 94.302, "None", 93.953, 119.713, "None", 92.163, "None", 143.991, 92.119, 126.073, "None", 98.352, 97.943, 97.904, 98.012, 98.048, 98.329, 104.034, 98.167, 98.575, 109.53, 113.466, 141.048, "None"], "lap": [1.0, 2.0, 3.0, 4.0, 5.0, 6.0, 7.0, 8.0, 9.0, 10.0, 11.0, 12.0, 13.0, 14.0, 15.0, 16.0, 17.0, 18.0, 19.0, 20.0, 21.0, 22.0, 23.0, 24.0, 25.0, 26.0, 27.0], "compound": ["HARD", "HARD", "HARD", "HARD", "HARD", "HARD", "HARD", "SOFT", "SOFT", "SOFT", "SOFT", "SOFT", "SOFT", "HARD", "HARD", "HARD", "HARD", "HARD", "HARD", "HARD", "HARD", "HARD", "HARD", "HARD", "HARD", "HARD", "HARD"], "stint": [1, 1, 1, 1, 1, 1, 1, 2, 2, 2, 2, 2, 2, 3, 3, 3, 3, 3, 3, 3, 3, 3, 3, 3, 3, 3, 3], "s1": ["None", 27.89, 47.175, 27.995, 46.474, 27.772, 34.482, "None", 27.336, 48.204, 46.029, 27.294, 38.803, "None", 28.991, 29.157, 28.904, 28.89, 28.961, 28.997, 29.133, 29.045, 29.142, 29.325, 29.086, 37.837, 59.351], "s2": [52.448, 39.989, 70.328, 39.792, 66.478, 39.769, 47.235, 57.12, 38.847, 70.729, 60.521, 38.8, 49.999, 43.149, 41.513, 41.297, 41.458, 41.554, 41.562, 41.656, 41.854, 41.62, 41.714, 52.249, 52.381, 58.024, 53.77], "s3": [37.616, 26.609, 52.545, 26.515, 49.232, 26.412, 37.996, 35.326, 25.98, 43.893, 37.441, 26.025, 37.271, 28.165, 27.848, 27.489, 27.542, 27.568, 27.525, 27.676, 33.047, 27.502, 27.719, 27.956, 31.999, 45.187, 44.883], "life": [1, 2, 3, 4, 5, 6, 7, 1, 2, 3, 4, 5, 6, 8, 9, 10, 11, 12, 13, 14, 15, 16, 17, 18, 19, 20, 21], "pos": ["None", "None", "None", "None", "None", "None", "None", "None", "None", "None", "None", "None", "None", "None", "None", "None", "None", "None", "None", "None", "None", "None", "None", "None", "None", "None", "None"], "status": ["1", "1", "1", "1", "1", "1", "1", "1", "1", "1", "1", "1", "1", "12", "1", "12", "1", "1", "1", "1", "1", "12", "1", "12", "2", "2", "21"], "pb": [false, true, false, true, false, true, false, false, true, false, false, true, false, false, false, false, false, false, false, false, false, false, false, false, false, false, false]}