{"time": ["None", 95.344, "None", 94.664, "None", 95.871, 131.946, "None", 94.976, 140.169, 113.335, "None", 93.868, "None", 93.936, 125.905, 94.973, 104.809, 114.789, 132.816], "lap": [1.0, 2.0, 3.0, 4.0, 5.0, 6.0, 7.0, 8.0, 9.0, 10.0, 11.0, 12.0, 13.0, 14.0, 15.0, 16.0, 17.0, 18.0, 19.0, 20.0], "compound": ["MEDIUM", "MEDIUM", "MEDIUM", "MEDIUM", "MEDIUM", "MEDIUM", "MEDIUM", "MEDIUM", "MEDIUM", "MEDIUM", "MEDIUM", "MEDIUM", "MEDIUM", "MEDIUM", "MEDIUM", "MEDIUM", "MEDIUM", "MEDIUM", "MEDIUM", "MEDIUM"], "stint": [1, 1, 1, 1, 1, 1, 1, 2, 2, 2, 2, 3, 3, 3, 3, 3, 3, 3, 3, 3], "s1": ["None", 30.494, 47.447, 30.112, 58.137, 31.003, 41.575, "None", 30.387, 42.824, 38.549, "None", 30.226, 51.842, 30.117, 38.922, 30.789, 34.374, 35.057, 63.467], "s2": [46.349, 40.888, 68.602, 40.639, 61.43, 41.021, 60.171, 52.039, 40.875, 69.032, 46.079, 49.763, 40.121, 72.598, 40.347, 59.137, 40.742, 45.432, 42.878, 42.201], "s3": [24.969, 23.962, 38.881, 23.913, 35.626, 23.847, 30.2, 29.124, 23.714, 28.313, 28.707, 26.441, 23.521, 27.34, 23.472, 27.846, 23.442, 25.003, 36.854, 27.148], "life": [1, 2, 3, 4, 5, 6, 7, 8, 9, 10, 11, 1, 2, 3, 4, 5, 6, 7, 8, 9], "pos": ["None", "None", "None", "None", "None", "None", "None", "None", "None", "None", "None", "None", "None", "None", "None", "None", "None", "None", "None", "None"], "status": ["1", "1", "1", "1", "1", "1", "1", "1", "1", "1", "1", "1", "1", "12", "1", "1", "1", "1", "1", "1"], "pb": [false, true, false, true, false, false, false, false, false, false, false, false, true, false, false, false, false, false, false, false]}