{"time": ["None", 90.806, 115.826, "None", 90.451, 115.724, "None", 90.363, 104.321, "None", 89.718, 119.366, "None", 90.445, 107.151, "None", 89.71, "None"], "lap": [1.0, 2.0, 3.0, 4.0, 5.0, 6.0, 7.0, 8.0, 9.0, 10.0, 11.0, 12.0, 13.0, 14.0, 15.0, 16.0, 17.0, 18.0], "compound": ["SOFT", "SOFT", "SOFT", "SOFT", "SOFT", "SOFT", "SOFT", "SOFT", "SOFT", "SOFT", "SOFT", "SOFT", "SOFT", "SOFT", "SOFT", "SOFT", "SOFT", "SOFT"], "stint": [1, 1, 1, 2, 2, 2, 3, 3, 3, 4, 4, 4, 5, 5, 5, 6, 6, 6], "s1": ["None", 29.108, 33.728, "None", 29.019, 36.484, "None", 29.029, 32.453, "None", 28.803, 34.993, "None", 29.175, 31.473, "None", 28.881, 37.881], "s2": [47.806, 38.989, 50.012, 45.75, 38.894, 49.879, 48.025, 38.777, 44.893, 48.69, 38.546, 51.379, 48.711, 38.747, 43.467, 51.747, 38.422, 53.351], "s3": [24.448, 22.709, 32.086, 24.349, 22.538, 29.361, 24.507, 22.557, 26.975, 26.238, 22.369, 32.994, 24.317, 22.523, 32.211, 27.434, 22.407, "None"], "life": [1, 2, 3, 1, 2, 3, 4, 5, 6, 1, 2, 3, 4, 5, 6, 1, 2, 3], "pos": ["None", "None", "None", "None", "None", "None", "None", "None", "None", "None", "None", "None", "None", "None", "None", "None", "None", "None"], "status": ["1", "1", "1", "1", "1", "1", "1", "1", "1", "1", "1", "1", "1", "1", "1", "1", "1", "1"], "pb": [false, true, false, false, true, false, false, true, false, false, true, false, false, true, false, false, true, false]}