{"time": ["None", 106.442, "None", 105.802, 142.111, "None", 126.373, 104.899, "None", 104.475, 119.741, "None", 111.084, 110.886, 117.304, 124.276, 111.541, 111.403, 112.917, 110.967, 111.228, 112.428, 149.516, "None"], "lap": [1.0, 2.0, 3.0, 4.0, 5.0, 6.0, 7.0, 8.0, 9.0, 10.0, 11.0, 12.0, 13.0, 14.0, 15.0, 16.0, 17.0, 18.0, 19.0, 20.0, 21.0, 22.0, 23.0, 24.0], "compound": ["MEDIUM", "MEDIUM", "MEDIUM", "MEDIUM", "MEDIUM", "SOFT", "SOFT", "SOFT", "SOFT", "SOFT", "SOFT", "MEDIUM", "MEDIUM", "MEDIUM", "MEDIUM", "MEDIUM", "MEDIUM", "MEDIUM", "MEDIUM", "MEDIUM", "MEDIUM", "MEDIUM", "MEDIUM", "MEDIUM"], "stint": [1, 1, 1, 1, 1, 2, 2, 2, 2, 2, 2, 3, 3, 3, 3, 3, 3, 3, 3, 3, 3, 3, 3, 3], "s1": ["None", 38.03, 58.906, 37.711, 47.289, "None", 46.463, 37.191, 58.991, 37.073, 40.966, "None", 39.93, 39.845, 40.829, 39.772, 40.068, 40.003, 41.208, 39.826, 39.86, 40.87, 51.666, 63.637], "s2": [47.669, 42.933, 63.65, 42.738, 59.99, 57.869, 52.301, 42.555, 64.793, 42.286, 46.353, 46.719, 45.016, 45.079, 48.722, 57.974, 45.346, 45.282, 45.518, 44.931, 45.29, 45.52, 56.867, 65.995], "s3": [27.048, 25.479, 31.47, 25.353, 34.832, 28.104, 27.609, 25.153, 29.362, 25.116, 32.422, 26.445, 26.138, 25.962, 27.753, 26.53, 26.127, 26.118, 26.191, 26.21, 26.078, 26.038, 40.983, 38.573], "life": [1, 2, 3, 4, 5, 1, 2, 3, 4, 5, 6, 6, 7, 8, 9, 10, 11, 12, 13, 14, 15, 16, 17, 18], "pos": ["None", "None", "None", "None", "None", "None", "None", "None", "None", "None", "None", "None", "None", "None", "None", "None", "None", "None", "None", "None", "None", "None", "None", "None"], "status": ["1", "1", "1", "12", "1", "12", "1", "1", "1", "1", "12", "1", "1", "1", "1", "12", "1", "12", "21", "1", "1", "12", "1", "1"], "pb": [false, true, false, true, false, false, false, true, false, true, false, false, false, false, false, false, false, false, false, false, false, false, false, false]}