{"time": ["None", 89.161, 125.43, 89.025, 136.895, 89.55, 119.738, "None", 87.381, 147.041, 87.557, 105.474, "None", 93.812, 93.141, 97.655], "lap": [1.0, 2.0, 3.0, 4.0, 5.0, 6.0, 7.0, 8.0, 9.0, 10.0, 11.0, 12.0, 13.0, 14.0, 15.0, 16.0], "compound": ["HARD", "HARD", "HARD", "HARD", "HARD", "HARD", "HARD", "SOFT", "SOFT", "SOFT", "SOFT", "SOFT", "HARD", "HARD", "HARD", "HARD"], "stint": [1, 1, 1, 1, 1, 1, 1, 2, 2, 2, 2, 2, 3, 3, 3, 3], "s1": ["None", 28.478, 41.142, 28.597, 42.61, 28.847, 37.418, "None", 27.987, 41.065, 28.003, 34.494, "None", 29.764, 29.601, 29.805], "s2": [40.768, 36.347, 50.746, 36.136, 54.176, 36.359, 49.447, 51.518, 35.45, 66.012, 35.583, 45.26, 39.585, 38.139, 37.772, 37.958], "s3": [33.023, 24.336, 33.542, 24.292, 40.109, 24.344, 32.873, 33.583, 23.944, 39.964, 23.971, 25.72, 25.929, 25.909, 25.768, 29.892], "life": [1, 2, 3, 4, 5, 6, 7, 1, 2, 3, 4, 5, 8, 9, 10, 11], "pos": ["None", "None", "None", "None", "None", "None", "None", "None", "None", "None", "None", "None", "None", "None", "None", "None"], "status": ["1", "1", "1", "1", "1", "1", "1", "1", "1", "1", "1", "1", "1", "1", "1", "1"], "pb": [false, true, false, true, false, false, false, false, true, false, false, false, false, false, false, false]}