{"time": ["None", 66.853, 84.781, "None", 65.924, 90.569, "None", 65.598, 92.79, "None", 65.657, 110.059, "None", 65.359, 83.506, "None", 65.335, "None"], "lap": [1.0, 2.0, 3.0, 4.0, 5.0, 6.0, 7.0, 8.0, 9.0, 10.0, 11.0, 12.0, 13.0, 14.0, 15.0, 16.0, 17.0, 18.0], "compound": ["SOFT", "SOFT", "SOFT", "SOFT", "SOFT", "SOFT", "SOFT", "SOFT", "SOFT", "SOFT", "SOFT", "SOFT", "SOFT", "SOFT", "SOFT", "SOFT", "SOFT", "SOFT"], "stint": [1, 1, 1, 2, 2, 2, 3, 3, 3, 4, 4, 4, 5, 5, 5, 6, 6, 6], "s1": ["None", 16.852, 18.705, "None", 16.573, 21.147, "None", 16.512, 20.084, "None", 16.535, 19.574, "None", 16.529, 19.275, "None", 16.452, 21.139], "s2": [40.999, 29.775, 35.661, 39.327, 29.542, 39.607, 39.356, 29.34, 40.768, 41.287, 29.32, 38.282, 39.828, 29.162, 35.299, 42.005, 29.146, 36.942], "s3": [25.72, 20.226, 30.415, 25.453, 19.809, 29.815, 24.732, 19.746, 31.938, 25.352, 19.802, 52.203, 25.485, 19.668, 28.932, 23.527, 19.737, "None"], "life": [7, 8, 9, 1, 2, 3, 1, 2, 3, 1, 2, 3, 1, 2, 3, 1, 2, 3], "pos": ["None", "None", "None", "None", "None", "None", "None", "None", "None", "None", "None", "None", "None", "None", "None", "None", "None", "None"], "status": ["1", "1", "1", "1", "1", "1", "1", "1", "1", "1", "1", "1", "1", "1", "1", "1", "1", "1"], "pb": [false, true, false, false, true, false, false, true, false, false, true, false, false, true, false, false, false, false]}